reflex_wordcloud/__init__.py
reflex_wordcloud/wordcloud.py
reflex_wordcloud-0.0.4.dist-info/METADATA
reflex_wordcloud-0.0.4.dist-info/WHEEL
reflex_wordcloud-0.0.4.dist-info/top_level.txt
reflex_wordcloud-0.0.4.dist-info/RECORD
